django_silly_auth/__init__.py
django_silly_auth/config.py
django_silly_auth/forms.py
django_silly_auth/mixins.py
django_silly_auth/serializers.py
django_silly_auth/translation.py
django_silly_auth/urls.py
django_silly_auth/utils.py
django_silly_auth/locale/django.pot
django_silly_auth/locale/en/LC_MESSAGES/django.mo
django_silly_auth/locale/en/LC_MESSAGES/django.po
django_silly_auth/locale/fr/LC_MESSAGES/django.mo
django_silly_auth/locale/fr/LC_MESSAGES/django.po
django_silly_auth/management/__init__.py
django_silly_auth/management/commands/__init__.py
django_silly_auth/management/commands/get_app_users.py
django_silly_auth/plop/__init__.py
django_silly_auth/plop/_users/__init__.py
django_silly_auth/plop/_users/admin.py
django_silly_auth/plop/_users/apps.py
django_silly_auth/plop/_users/forms.py
django_silly_auth/plop/_users/models.py
django_silly_auth/templates/__init__.py
django_silly_auth/templates/silly_auth/__init__.py
django_silly_auth/templates/silly_auth/_base.html
django_silly_auth/templates/silly_auth/_try/__init__.py
django_silly_auth/templates/silly_auth/_try/_base.html
django_silly_auth/templates/silly_auth/_try/_single_page.html
django_silly_auth/templates/silly_auth/_try/_users.html
django_silly_auth/templates/silly_auth/classic/__init__.py
django_silly_auth/templates/silly_auth/classic/account.html
django_silly_auth/templates/silly_auth/classic/change_email.html
django_silly_auth/templates/silly_auth/classic/change_username.html
django_silly_auth/templates/silly_auth/classic/index.html
django_silly_auth/templates/silly_auth/classic/login.html
django_silly_auth/templates/silly_auth/classic/request_password_reset.html
django_silly_auth/templates/silly_auth/classic/request_resend_account_confirmation_email.html
django_silly_auth/templates/silly_auth/classic/reset_password.html
django_silly_auth/templates/silly_auth/classic/signup.html
django_silly_auth/templates/silly_auth/emails/__init__.py
django_silly_auth-1.1.9.dist-info/LICENSE.md
django_silly_auth-1.1.9.dist-info/METADATA
django_silly_auth-1.1.9.dist-info/WHEEL
django_silly_auth-1.1.9.dist-info/top_level.txt
django_silly_auth-1.1.9.dist-info/RECORD
