Metadata-Version: 2.1
Name: django-silly-auth
Version: 1.1.9
Summary: Authentication package for Django and DRF
Home-page: https://github.com/byoso/django_silly_auth
Author: Vincent Fabre
Author-email: peigne.plume@gmail.com
License: MIT
Keywords: django auth drf jwt
Platform: UNKNOWN
Classifier: License :: OSI Approved :: MIT License
Classifier: Programming Language :: Python :: 3
Classifier: Development Status :: 4 - Beta
Classifier: License :: OSI Approved :: MIT License
Classifier: Natural Language :: English
Requires-Python: >=3.10
License-File: LICENSE.md
Requires-Dist: pyjwt (>=2.6.0)
